math_magic/__init__.py
math_magic/basic_math.py
math_magic-0.0.1.dist-info/LICENSE
math_magic-0.0.1.dist-info/METADATA
math_magic-0.0.1.dist-info/WHEEL
math_magic-0.0.1.dist-info/top_level.txt
math_magic-0.0.1.dist-info/RECORD
