Metadata-Version: 2.1
Name: math-magic
Version: 0.0.1
Summary: For basic math calculations
Home-page: https://github.com/dmonisankar/math_magic
Author: Monisankar Das
Author-email: das.monisankar@gmail.com
License: UNKNOWN
Platform: UNKNOWN
Classifier: Programming Language :: Python :: 3
Classifier: License :: OSI Approved :: MIT License
Classifier: Operating System :: OS Independent
Requires-Python: >=3.7
